{
  "pulled_at_utc": "2026-03-11T18:29:36.445685+00:00",
  "summary": {
    "report_date": "2026-03-11T18:16:16.331Z",
    "customers_out": 1821,
    "total_customers": 2820992,
    "pct_out": 0.07,
    "total_outages": 48
  },
  "outages": [
    {
      "lat": 38.04397,
      "lng": -77.35699,
      "customers": 3,
      "cause": "Equipment Upgrade",
      "crew_status": "Working",
      "etr": "Today at 3:00 PM - 6:00 PM",
      "incident_id": "34727411",
      "provider": "Dominion Energy"
    },
    {
      "lat": 37.45409,
      "lng": -77.19465,
      "customers": 2,
      "cause": "Equipment Upgrade",
      "crew_status": "Working",
      "etr": "Today at 1:00 PM - 4:00 PM",
      "incident_id": "34727122",
      "provider": "Dominion Energy"
    },
    {
      "lat": 36.66912,
      "lng": -77.56041,
      "customers": 2,
      "cause": "Pending Investigation",
      "crew_status": "Working",
      "etr": "Today at 4:00 PM - 7:00 PM",
      "incident_id": "34727540",
      "provider": "Dominion Energy"
    },
    {
      "lat": 37.82979,
      "lng": -76.69648,
      "customers": 2,
      "cause": "EQUIPMENT PROBLEM",
      "crew_status": "Dispatched",
      "etr": "Today at 5:00 PM - 8:00 PM",
      "incident_id": "34727526",
      "provider": "Dominion Energy"
    },
    {
      "lat": 38.9959,
      "lng": -77.79379,
      "customers": 2,
      "cause": "Equipment Upgrade",
      "crew_status": "Working",
      "etr": "Today at 5:00 PM - 8:00 PM",
      "incident_id": "34727624",
      "provider": "Dominion Energy"
    },
    {
      "lat": 36.83138,
      "lng": -75.97755,
      "customers": 1,
      "cause": "Pending Investigation",
      "crew_status": "Awaiting Assignment",
      "etr": "Today at 4:00 PM - 7:00 PM",
      "incident_id": "34727635",
      "provider": "Dominion Energy"
    },
    {
      "lat": 37.2618,
      "lng": -76.90111,
      "customers": 1,
      "cause": "Power Line Damaged",
      "crew_status": "Dispatched",
      "etr": "Today at 4:00 PM - 7:00 PM",
      "incident_id": "34727275",
      "provider": "Dominion Energy"
    },
    {
      "lat": 37.20528,
      "lng": -77.35687,
      "customers": 1,
      "cause": "Equipment Upgrade",
      "crew_status": "Working",
      "etr": "Today at 4:00 PM - 7:00 PM",
      "incident_id": "34727455",
      "provider": "Dominion Energy"
    },
    {
      "lat": 38.32866,
      "lng": -77.63806,
      "customers": 1,
      "cause": "Pending Investigation",
      "crew_status": "Dispatched",
      "etr": "Today at 6:00 PM - 9:00 PM",
      "incident_id": "34727632",
      "provider": "Dominion Energy"
    }
  ]
}
