{
  "pulled_at_utc": "2026-03-17T22:26:34.904684+00:00",
  "summary": {
    "report_date": "2026-03-17T22:16:07.785Z",
    "customers_out": 2760,
    "total_customers": 2820593,
    "pct_out": 0.1,
    "total_outages": 101
  },
  "outages": [
    {
      "lat": 35.74837,
      "lng": -77.05191,
      "customers": 77,
      "cause": "Pending Investigation",
      "crew_status": "Dispatched",
      "etr": "Tomorrow at 2:00 AM - 7:00 AM",
      "incident_id": "34738506",
      "provider": "Dominion Energy"
    },
    {
      "lat": 37.20923,
      "lng": -76.60961,
      "customers": 12,
      "cause": "Pending Investigation",
      "crew_status": "Dispatched",
      "etr": "Today at 9:00 PM - Tomorrow at 2:00 AM",
      "incident_id": "34738601",
      "provider": "Dominion Energy"
    },
    {
      "lat": 37.596,
      "lng": -76.97395,
      "customers": 3,
      "cause": "Storm",
      "crew_status": "Dispatched",
      "etr": "Today at 7:00 PM - Tomorrow at 12:00 AM",
      "incident_id": "34738390",
      "provider": "Dominion Energy"
    },
    {
      "lat": 36.21517,
      "lng": -76.71153,
      "customers": 1,
      "cause": "Pending Investigation",
      "crew_status": "Awaiting Assignment",
      "etr": "Today at 8:00 PM - Tomorrow at 1:00 AM",
      "incident_id": "34738629",
      "provider": "Dominion Energy"
    },
    {
      "lat": 36.77449,
      "lng": -76.99589,
      "customers": 1,
      "cause": "Power Line Damaged",
      "crew_status": "Awaiting Assignment",
      "etr": "Today at 5:00 PM - 10:00 PM",
      "incident_id": "34738394",
      "provider": "Dominion Energy"
    },
    {
      "lat": 38.34152,
      "lng": -77.05655,
      "customers": 1,
      "cause": "Storm",
      "crew_status": "Dispatched",
      "etr": "Today at 6:00 PM - 11:00 PM",
      "incident_id": "34738191",
      "provider": "Dominion Energy"
    },
    {
      "lat": 37.73904,
      "lng": -76.47216,
      "customers": 1,
      "cause": "Storm",
      "crew_status": "Dispatched",
      "etr": "Today at 6:00 PM - 11:00 PM",
      "incident_id": "34738310",
      "provider": "Dominion Energy"
    },
    {
      "lat": 38.70582,
      "lng": -77.60265,
      "customers": 1,
      "cause": "Pending Investigation",
      "crew_status": "Awaiting Assignment",
      "etr": "Today at 7:00 PM - Tomorrow at 12:00 AM",
      "incident_id": "34738508",
      "provider": "Dominion Energy"
    }
  ]
}
