{
  "pulled_at_utc": "2026-03-27T11:01:18.418168+00:00",
  "summary": {
    "report_date": "2026-03-27T10:46:01.500Z",
    "customers_out": 107,
    "total_customers": 2820654,
    "pct_out": 0.01,
    "total_outages": 6
  },
  "outages": [
    {
      "lat": 36.22791,
      "lng": -77.10992,
      "customers": 4,
      "cause": "Pending Investigation",
      "crew_status": "Awaiting Assignment",
      "etr": "Reassessing Condition",
      "incident_id": "34741155",
      "provider": "Dominion Energy"
    },
    {
      "lat": 37.11786,
      "lng": -76.3467,
      "customers": 1,
      "cause": "EQUIPMENT PROBLEM",
      "crew_status": "Dispatched",
      "etr": "Today at 6:00 AM - 9:00 AM",
      "incident_id": "34748077",
      "provider": "Dominion Energy"
    }
  ]
}
