{
  "pulled_at_utc": "2026-03-22T19:57:38.894544+00:00",
  "summary": {
    "report_date": "2026-03-22T19:46:04.698Z",
    "customers_out": 394,
    "total_customers": 2820593,
    "pct_out": 0.02,
    "total_outages": 20
  },
  "outages": [
    {
      "lat": 37.5717,
      "lng": -78.22983,
      "customers": 157,
      "cause": "Pending Investigation",
      "crew_status": "Dispatched",
      "etr": "Today at 8:00 PM - 11:00 PM",
      "incident_id": "34742917",
      "provider": "Dominion Energy"
    },
    {
      "lat": 38.04853,
      "lng": -78.04198,
      "customers": 110,
      "cause": "Broken Pole",
      "crew_status": "Working",
      "etr": "Today at 6:00 PM - 9:00 PM",
      "incident_id": "34742862",
      "provider": "Dominion Energy"
    },
    {
      "lat": 36.22791,
      "lng": -77.10992,
      "customers": 4,
      "cause": "Pending Investigation",
      "crew_status": "Awaiting Assignment",
      "etr": "Reassessing Condition",
      "incident_id": "34741155",
      "provider": "Dominion Energy"
    },
    {
      "lat": 36.06909,
      "lng": -77.48359,
      "customers": 3,
      "cause": "Pending Investigation",
      "crew_status": "Dispatched",
      "etr": "Today at 5:00 PM - 8:00 PM",
      "incident_id": "34742884",
      "provider": "Dominion Energy"
    },
    {
      "lat": 39.10183,
      "lng": -77.74832,
      "customers": 1,
      "cause": "Pending Investigation",
      "crew_status": "Dispatched",
      "etr": "Today at 1:00 PM - 4:00 PM",
      "incident_id": "34742808",
      "provider": "Dominion Energy"
    },
    {
      "lat": 36.69039,
      "lng": -76.2652,
      "customers": 1,
      "cause": "Emergency work",
      "crew_status": "Working",
      "etr": "Today at 6:00 PM - 9:00 PM",
      "incident_id": "34742918",
      "provider": "Dominion Energy"
    },
    {
      "lat": 37.59714,
      "lng": -77.53167,
      "customers": 1,
      "cause": "Power Line Damaged",
      "crew_status": "Dispatched",
      "etr": "Today at 1:00 PM - 4:00 PM",
      "incident_id": "34742816",
      "provider": "Dominion Energy"
    },
    {
      "lat": 37.6489,
      "lng": -77.80189,
      "customers": 1,
      "cause": "Pending Investigation",
      "crew_status": "Working",
      "etr": "Today at 3:00 PM - 6:00 PM",
      "incident_id": "34742802",
      "provider": "Dominion Energy"
    },
    {
      "lat": 38.29909,
      "lng": -77.47019,
      "customers": 1,
      "cause": "Pending Investigation",
      "crew_status": "Dispatched",
      "etr": "Today at 6:00 PM - 9:00 PM",
      "incident_id": "34742879",
      "provider": "Dominion Energy"
    },
    {
      "lat": 38.05827,
      "lng": -78.48896,
      "customers": 1,
      "cause": "Pending Investigation",
      "crew_status": "Working",
      "etr": "Pending Investigation",
      "incident_id": "34742739",
      "provider": "Dominion Energy"
    }
  ]
}
