{
  "pulled_at_utc": "2026-03-09T14:38:28.625434+00:00",
  "summary": {
    "report_date": "2026-03-09T14:30:54.163Z",
    "customers_out": 900,
    "total_customers": 2820992,
    "pct_out": 0.04,
    "total_outages": 70
  },
  "outages": [
    {
      "lat": 35.90846,
      "lng": -77.14401,
      "customers": 5,
      "cause": "Pending Investigation",
      "crew_status": "Dispatched",
      "etr": "Today at 11:00 AM - 2:00 PM",
      "incident_id": "34724669",
      "provider": "Dominion Energy"
    },
    {
      "lat": 38.00358,
      "lng": -78.79761,
      "customers": 3,
      "cause": "Pending Investigation",
      "crew_status": "Awaiting Assignment",
      "etr": "Today at 3:00 PM - 6:00 PM",
      "incident_id": "34724828",
      "provider": "Dominion Energy"
    },
    {
      "lat": 37.66296,
      "lng": -76.96521,
      "customers": 3,
      "cause": "Equipment Upgrade",
      "crew_status": "Working",
      "etr": "Today at 1:00 PM - 4:00 PM",
      "incident_id": "34724746",
      "provider": "Dominion Energy"
    },
    {
      "lat": 37.82244,
      "lng": -79.39399,
      "customers": 1,
      "cause": "Equipment Upgrade",
      "crew_status": "Working",
      "etr": "Today at 11:00 AM - 2:00 PM",
      "incident_id": "34724667",
      "provider": "Dominion Energy"
    },
    {
      "lat": 37.40191,
      "lng": -77.11501,
      "customers": 1,
      "cause": "Pending Investigation",
      "crew_status": "Dispatched",
      "etr": "Today at 2:00 PM - 5:00 PM",
      "incident_id": "34724818",
      "provider": "Dominion Energy"
    },
    {
      "lat": 37.05997,
      "lng": -78.47592,
      "customers": 1,
      "cause": "Pending Investigation",
      "crew_status": "Awaiting Assignment",
      "etr": "Today at 1:00 PM - 4:00 PM",
      "incident_id": "34724750",
      "provider": "Dominion Energy"
    },
    {
      "lat": 37.387,
      "lng": -78.36742,
      "customers": 1,
      "cause": "Pending Investigation",
      "crew_status": "Dispatched",
      "etr": "Today at 2:00 PM - 5:00 PM",
      "incident_id": "34724821",
      "provider": "Dominion Energy"
    },
    {
      "lat": 38.3384,
      "lng": -77.06488,
      "customers": 1,
      "cause": "Pending Investigation",
      "crew_status": "Dispatched",
      "etr": "Today at 2:00 PM - 5:00 PM",
      "incident_id": "34724766",
      "provider": "Dominion Energy"
    }
  ]
}
